[
	{
		"tag": "Hugging Face",
		"title": "Introduction to the 🤗 Accelerated Inference API in Svelte",
		"preview": "Hugging Face is the easiest way to build, train, and deploy machine learning models.&nbsp;",
		"url": "http://localhost:3000/tutorials/huggingface"
	},
	{
		"tag": "Component",
		"title": "Simple Table",
		"preview": "A simple sveltey table",
		"url": "/tutorials/simple-table"
	},
	{
		"tag": "REPL",
		"title": "REPL Scratchpad",
		"preview": "Getting started with SvelteKit and Tailwind.",
		"url": "/tutorials/repl"
	}
]
